README.rst
setup.py
airpy/__init__.py
airpy/autopilot.py
airpy/install.py
airpy/list.py
airpy/main.py
airpy/remove.py
airpy/start.py
airpy/utils.py
airpy.egg-info/PKG-INFO
airpy.egg-info/SOURCES.txt
airpy.egg-info/dependency_links.txt
airpy.egg-info/entry_points.txt
airpy.egg-info/requires.txt
airpy.egg-info/top_level.txt