Metadata-Version: 1.0
Name: airpy
Version: 0.0.3
Summary: Documentation Installer for the Pythonic Soul
Home-page: https://github.com/kevinaloys/airpy
Author: Kevin Aloysius
Author-email: kevinaloysius25@gmail.com
License: MIT
Platform: UNKNOWN
